eo4eu_meta_utils/__init__.py
eo4eu_meta_utils/test/__init__.py
eo4eu_meta_utils/test/app.py
eo4eu_meta_utils/test/commands.py
eo4eu_meta_utils/test/config.py
eo4eu_meta_utils/test/defaults.py
eo4eu_meta_utils/test/logs.py
eo4eu_meta_utils/test/message.py
eo4eu_meta_utils/test/recipe.py
eo4eu_meta_utils/test/server.py
eo4eu_meta_utils-0.8.0.dist-info/METADATA
eo4eu_meta_utils-0.8.0.dist-info/WHEEL
eo4eu_meta_utils-0.8.0.dist-info/entry_points.txt
eo4eu_meta_utils-0.8.0.dist-info/top_level.txt
eo4eu_meta_utils-0.8.0.dist-info/RECORD
